{
    "covered_lines": {
        "Apache Commons Collections.org.apache.commons.collections4.comparators.ComparableComparator": [
            "49",
            "75",
            "76",
            "93"
        ],
        "Apache Commons Collections.org.apache.commons.collections4.comparators.ComparatorChain": [
            "108",
            "109",
            "126",
            "127",
            "128",
            "129",
            "254",
            "268",
            "269",
            "273",
            "276",
            "277",
            "287"
        ]
    },
    "covered_stats": {
        "Apache Commons Collections.org.apache.commons.collections4.comparators.ComparableComparator.ComparableComparator()": {
            "branch_coverage": "n/a",
            "line_coverage": "100%",
            "missed_complexity": "0",
            "missed_lines": "0",
            "missed_methods": "0",
            "total_complexity": "1",
            "total_lines": "2",
            "total_methods": "1"
        },
        "Apache Commons Collections.org.apache.commons.collections4.comparators.ComparableComparator.compare(Comparable, Comparable)": {
            "branch_coverage": "n/a",
            "line_coverage": "100%",
            "missed_complexity": "0",
            "missed_lines": "0",
            "missed_methods": "0",
            "total_complexity": "1",
            "total_lines": "1",
            "total_methods": "1"
        },
        "Apache Commons Collections.org.apache.commons.collections4.comparators.ComparableComparator.static {...}": {
            "branch_coverage": "n/a",
            "line_coverage": "100%",
            "missed_complexity": "0",
            "missed_lines": "0",
            "missed_methods": "0",
            "total_complexity": "1",
            "total_lines": "1",
            "total_methods": "1"
        },
        "Apache Commons Collections.org.apache.commons.collections4.comparators.ComparatorChain.ComparatorChain(List)": {
            "branch_coverage": "n/a",
            "line_coverage": "100%",
            "missed_complexity": "0",
            "missed_lines": "0",
            "missed_methods": "0",
            "total_complexity": "1",
            "total_lines": "2",
            "total_methods": "1"
        },
        "Apache Commons Collections.org.apache.commons.collections4.comparators.ComparatorChain.ComparatorChain(List, BitSet)": {
            "branch_coverage": "n/a",
            "line_coverage": "100%",
            "missed_complexity": "0",
            "missed_lines": "0",
            "missed_methods": "0",
            "total_complexity": "1",
            "total_lines": "6",
            "total_methods": "1"
        },
        "Apache Commons Collections.org.apache.commons.collections4.comparators.ComparatorChain.checkChainIntegrity()": {
            "branch_coverage": "50%",
            "line_coverage": "50%",
            "missed_complexity": "1",
            "missed_lines": "1",
            "missed_methods": "0",
            "total_complexity": "2",
            "total_lines": "3",
            "total_methods": "1"
        },
        "Apache Commons Collections.org.apache.commons.collections4.comparators.ComparatorChain.compare(Object, Object)": {
            "branch_coverage": "40%",
            "line_coverage": "76%",
            "missed_complexity": "5",
            "missed_lines": "4",
            "missed_methods": "0",
            "total_complexity": "6",
            "total_lines": "14",
            "total_methods": "1"
        }
    }
}